sphinx_testify/__init__.py
sphinx_testify/directive.py
sphinx_testify/error.py
sphinx_testify/report_parser.py
sphinx_testify/test_result.py
sphinx_testify-0.1.1.dist-info/METADATA
sphinx_testify-0.1.1.dist-info/WHEEL
sphinx_testify-0.1.1.dist-info/licenses/COPYING
sphinx_testify-0.1.1.dist-info/RECORD
