Metadata-Version: 2.4
Name: sphinx-testify
Version: 0.1.1
Summary: A Sphinx directive which enables testifying documentation by explicitly referencing test results
Project-URL: Homepage, https://github.com/BasicWolf/sphinx-testify
Project-URL: Issues, https://github.com/BasicWolf/sphinx-testify/issues
Author-email: Zaur Nasibov <zaur@zaurnasibov.com>
License-File: COPYING
Classifier: License :: OSI Approved :: GNU Lesser General Public License v3 (LGPLv3)
Classifier: Operating System :: OS Independent
Classifier: Programming Language :: Python :: 3
Requires-Python: >=3.12
